main.py
mcp_weatherserver_wsd-0.1.1.dist-info/METADATA
mcp_weatherserver_wsd-0.1.1.dist-info/WHEEL
mcp_weatherserver_wsd-0.1.1.dist-info/entry_points.txt
mcp_weatherserver_wsd-0.1.1.dist-info/top_level.txt
mcp_weatherserver_wsd-0.1.1.dist-info/RECORD
