Metadata-Version: 2.4
Name: MCP-WeatherServer_wsd
Version: 0.1.1
Summary: 尝试学习，mcp，获取天气
Requires-Python: >=3.11
Requires-Dist: build>=1.2.2.post1
Requires-Dist: httpx>=0.28.1
Requires-Dist: mcp>=1.7.1
Requires-Dist: requests>=2.32.3
